LICENSE
MANIFEST.in
README.md
quicktest.py
settings_test.py
setup.py
django_vkontakte_users.egg-info/PKG-INFO
django_vkontakte_users.egg-info/SOURCES.txt
django_vkontakte_users.egg-info/dependency_links.txt
django_vkontakte_users.egg-info/not-zip-safe
django_vkontakte_users.egg-info/requires.txt
django_vkontakte_users.egg-info/top_level.txt
vkontakte_users/__init__.py
vkontakte_users/__init__.pyc
vkontakte_users/admin.py
vkontakte_users/admin.pyc
vkontakte_users/factories.py
vkontakte_users/factories.pyc
vkontakte_users/mixins.pyc
vkontakte_users/models.py
vkontakte_users/models.pyc
vkontakte_users/signals.py
vkontakte_users/tasks.py
vkontakte_users/tests.py
vkontakte_users/tests.pyc
vkontakte_users/migrations/0001_initial.py
vkontakte_users/migrations/0001_initial.pyc
vkontakte_users/migrations/0002_auto_20160213_0238.py
vkontakte_users/migrations/0002_auto_20160213_0238.pyc
vkontakte_users/migrations/0003_auto_20160215_1510.py
vkontakte_users/migrations/0003_auto_20160215_1510.pyc
vkontakte_users/migrations/__init__.py
vkontakte_users/migrations/__init__.pyc